anqa/rest/__init__.py
anqa/rest/_version.py
anqa/rest/errors/__init__.py
anqa/rest/errors/exceptions.py
anqa/rest/errors/handlers.py
anqa/rest/errors/models.py
anqa/rest/errors/utils.py
anqa/rest/factory.py
anqa/rest/openapi.py
anqa/rest/prometheus.py
anqa/rest/py.typed
anqa/rest/response.py
anqa/rest/routers.py
anqa/rest/serializer.py
anqa/rest/settings.py
anqa/rest/views/__init__.py
anqa/rest/views/functools.py
anqa/rest/views/generics.py
anqa/rest/views/mixins.py
anqa/rest/views/views.py
anqa/rest/views/viewsets.py
anqa_rest-0.0.1.dist-info/METADATA
anqa_rest-0.0.1.dist-info/WHEEL
anqa_rest-0.0.1.dist-info/RECORD
