Metadata-Version: 2.1
Name: anqa-rest
Version: 0.0.1
Summary: 
Requires-Python: >=3.8.1,<4.0
Classifier: Programming Language :: Python :: 3
Classifier: Programming Language :: Python :: 3.9
Classifier: Programming Language :: Python :: 3.10
Classifier: Programming Language :: Python :: 3.11
Requires-Dist: anqa-core (==0.0.1)
Requires-Dist: fastapi (>=0.94.1,<0.95.0)
Requires-Dist: starlette-exporter (>=0.15.1,<0.16.0)
Requires-Dist: uvicorn (>=0.21.1,<0.22.0)
